VLAD/Descriptors.py
VLAD/ImageDataset.py
VLAD/__init__.py
VLAD/utils.py
VLAD/vlad.py
VLAD-0.1.7.dist-info/LICENSE
VLAD-0.1.7.dist-info/METADATA
VLAD-0.1.7.dist-info/WHEEL
VLAD-0.1.7.dist-info/top_level.txt
VLAD-0.1.7.dist-info/RECORD
