Metadata-Version: 2.1
Name: VLAD
Version: 0.1.7
Summary: VLAD (Vector of Locally Aggregated Descriptors) implementation using opencv's SIFT and sklearn's KMeans
Author-email: ginofft <ntnghia.andrei@gmail.com>
License: MIT License
Keywords: vlad,image retrieval,computer vision
License-File: LICENSE
Requires-Dist: opencv-python
Requires-Dist: torch
Requires-Dist: scikit-learn
Requires-Dist: numpy
Requires-Dist: h5py
Requires-Dist: matplotlib
